{
  "slug": "introduction",
  "title": "1. \ud504\ub808\uc784\uc6cc\ud06c \uc18c\uac1c",
  "category": "basic",
  "content": "# 1. \ud504\ub808\uc784\uc6cc\ud06c \uc18c\uac1c\n\n[\u2190 \ubaa9\ucc28\ub85c \ub3cc\uc544\uac00\uae30](README.md)\n\n---\n\n## \uac1c\uc694\n\n\ub9d1\uc740\ud504\ub808\uc784\uc6cc\ud06c\ub294 \uc790\ubc14 \uc6f9\uac1c\ubc1c \ud504\ub808\uc784\uc6cc\ud06c\uc785\ub2c8\ub2e4. WAS(Web Application Server) \uc548\uc5d0\uc11c \uad6c\ub3d9\ub418\ub294 \uc194\ub8e8\uc158\uc774\uba70, \uac04\uacb0\ud558\uace0 \ud6a8\uc728\uc801\uc778 \uc6f9 \uc560\ud50c\ub9ac\ucf00\uc774\uc158 \uac1c\ubc1c\uc744 \uc9c0\uc6d0\ud569\ub2c8\ub2e4.\n\n---\n\n## \uc8fc\uc694 \ud2b9\uc9d5\n\n### 1. \ud15c\ud50c\ub9bf \uc5d4\uc9c4\n- \ud504\ub85c\uadf8\ub7a8 \ub85c\uc9c1\uacfc \ud654\uba74 \ucd9c\ub825\uc744 \uc644\uc804\ud788 \ubd84\ub9ac\n- \uc6f9\ub514\uc790\uc774\ub108/\ud37c\ube14\ub9ac\uc154\uac00 \uc27d\uac8c \uc218\uc815 \uac00\ub2a5\ud55c \ub2e8\uc21c\ud654\ub41c \ubb38\ubc95\n- \ubcc0\uc218 \uce58\ud658, \ub8e8\ud504, \uc870\uac74\ubb38, \ub808\uc774\uc544\uc6c3 \uae30\ub2a5 \uc81c\uacf5\n\n### 2. DataSet \uac1d\uccb4\n- \ubaa8\ub4e0 \ub370\uc774\ud130\ub97c \ud1b5\uc77c\ub41c \ud615\ud0dc\ub85c \ucc98\ub9ac\n- \ub370\uc774\ud130\ubca0\uc774\uc2a4, XML, Excel \ub4f1 \ub2e4\uc591\ud55c \uc18c\uc2a4 \uc9c0\uc6d0\n- JSON \uc9c1\ub82c\ud654/\uc5ed\uc9c1\ub82c\ud654 \uc9c0\uc6d0\n\n### 3. \ub370\uc774\ud130\ubca0\uc774\uc2a4 \ucd94\uc0c1\ud654\n- Oracle, MySQL, MSSQL, DB2 \ub4f1 \ub2e4\uc591\ud55c DBMS \uc9c0\uc6d0\n- DAO \ud328\ud134\uc744 \ud1b5\ud55c \uae54\ub054\ud55c \ub370\uc774\ud130\ubca0\uc774\uc2a4 \ucc98\ub9ac\n- Connection Pool \uc790\ub3d9 \uad00\ub9ac\n\n### 4. \uc720\ud6a8\uc131 \uac80\uc99d\n- \ud55c \ubc88\uc758 \uc124\uc815\uc73c\ub85c \uc11c\ubc84/\ud074\ub77c\uc774\uc5b8\ud2b8 \uc591\uce21 \uac80\uc99d\n- \ub2e4\uc591\ud55c \uae30\ubcf8 \uac80\uc99d \uaddc\uce59 \uc81c\uacf5\n- \uc0ac\uc6a9\uc790 \uc815\uc758 \uac80\uc99d \uaddc\uce59 \ucd94\uac00 \uac00\ub2a5\n\n### 5. \uac04\ub2e8\ud55c \uc124\uc815\n- \ucd5c\uc18c\ud55c\uc758 \ud658\uacbd\uc124\uc815 \ud30c\uc77c\n- XML \uae30\ubc18\uc758 \uc9c1\uad00\uc801\uc778 \uc124\uc815\n- \uc6b4\uc601 \uc911 \uc124\uc815 \ubcc0\uacbd \uac00\ub2a5 (\uc7ac\uc2dc\uc791 \ubd88\ud544\uc694)\n\n---\n\n## \uc544\ud0a4\ud14d\ucc98\n\n### MVC \ud328\ud134 \uae30\ubc18\n\n```\n[Browser]\n    \u2193 Request\n[JSP Controller]\n    \u2193\n[Model (DAO/DataSet)]\n    \u2193\n[Database]\n    \u2191\n[View (Template)]\n    \u2193 Response\n[Browser]\n```\n\n### \uc8fc\uc694 \uad6c\uc131 \uc694\uc18c\n\n1. **Controller**: JSP \ud30c\uc77c\n   - \uc694\uccad \ucc98\ub9ac\n   - \ube44\uc988\ub2c8\uc2a4 \ub85c\uc9c1 \uc2e4\ud589\n   - \ub370\uc774\ud130 \uc900\ube44\n\n2. **Model**: DAO \ud074\ub798\uc2a4 + DataSet\n   - \ub370\uc774\ud130\ubca0\uc774\uc2a4 \uc5f0\ub3d9\n   - \ube44\uc988\ub2c8\uc2a4 \ub85c\uc9c1\n   - \ub370\uc774\ud130 \uad00\ub9ac\n\n3. **View**: HTML \ud15c\ud50c\ub9bf\n   - \ud654\uba74 \ucd9c\ub825\n   - \ub370\uc774\ud130 \ud45c\uc2dc\n   - \uc0ac\uc6a9\uc790 \uc778\ud130\ud398\uc774\uc2a4\n\n---\n\n## \ud575\uc2ec \ud074\ub798\uc2a4\n\n### Malgn\n\uc720\ud2f8\ub9ac\ud2f0 \uba54\uc18c\ub4dc\ub97c \uc81c\uacf5\ud558\ub294 \ud575\uc2ec \ud074\ub798\uc2a4\n\n**\uc8fc\uc694 \uba54\uc18c\ub4dc**:\n- `p()`: \ub514\ubc84\uae45 \ucd9c\ub825\n- `isPost()`: POST \ubc29\uc2dd \uccb4\ud06c\n- `jsError()`: \uc5d0\ub7ec \uba54\uc2dc\uc9c0 + \uc774\uc804 \ud398\uc774\uc9c0 \uc774\ub3d9\n- `jsAlert()`: \uc54c\ub9bc \uba54\uc2dc\uc9c0\n- `jsReplace()`: \ud398\uc774\uc9c0 \uc774\ub3d9\n- `time()`: \ub0a0\uc9dc/\uc2dc\uac04 \ud3ec\ub9f7\ud305\n\n### Form\n\ud3fc \ub370\uc774\ud130 \ucc98\ub9ac \ubc0f \uc720\ud6a8\uc131 \uac80\uc99d\n\n**\uc8fc\uc694 \uba54\uc18c\ub4dc**:\n- `addElement()`: \ud3fc \ud56d\ubaa9 \uc815\uc758\n- `validate()`: \uc720\ud6a8\uc131 \uac80\uc99d\n- `get()`: \ud3fc \ub370\uc774\ud130 \uac00\uc838\uc624\uae30\n- `getScript()`: \ud074\ub77c\uc774\uc5b8\ud2b8 \uac80\uc99d \uc2a4\ud06c\ub9bd\ud2b8 \uc0dd\uc131\n\n### Page\n\ud15c\ud50c\ub9bf \ucc98\ub9ac\n\n**\uc8fc\uc694 \uba54\uc18c\ub4dc**:\n- `setLayout()`: \ub808\uc774\uc544\uc6c3 \uc9c0\uc815\n- `setBody()`: \ud15c\ud50c\ub9bf \uc9c0\uc815\n- `setVar()`: \ubcc0\uc218 \uc124\uc815\n- `setLoop()`: \ub8e8\ud504 \ub370\uc774\ud130 \uc124\uc815\n- `display()`: \ud654\uba74 \ucd9c\ub825\n\n### DataObject\n\ub370\uc774\ud130\ubca0\uc774\uc2a4 \uae30\ubcf8 \uc5f0\ub3d9\n\n**\uc8fc\uc694 \uba54\uc18c\ub4dc**:\n- `query()`: SELECT \ucffc\ub9ac \uc2e4\ud589\n- `execute()`: INSERT/UPDATE/DELETE \uc2e4\ud589\n- `find()`: \uc870\uac74\uc73c\ub85c \uac80\uc0c9\n- `item()`: \ub370\uc774\ud130 \ud56d\ubaa9 \uc124\uc815\n- `insert()`: \ub370\uc774\ud130 \uc0bd\uc785\n- `update()`: \ub370\uc774\ud130 \uc218\uc815\n- `delete()`: \ub370\uc774\ud130 \uc0ad\uc81c\n\n### DataSet\n\ub370\uc774\ud130 \uc800\uc7a5 \ubc0f \ucc98\ub9ac\n\n**\uc8fc\uc694 \uba54\uc18c\ub4dc**:\n- `addRow()`: \ud589 \ucd94\uac00\n- `next()`: \ub2e4\uc74c \ud589\uc73c\ub85c \uc774\ub3d9\n- `put()`: \ub370\uc774\ud130 \uc124\uc815\n- `get()` / `s()` / `i()`: \ub370\uc774\ud130 \uac00\uc838\uc624\uae30\n- `serialize()`: JSON \uc9c1\ub82c\ud654\n- `unserialize()`: JSON \uc5ed\uc9c1\ub82c\ud654\n\n### ListManager\n\ubaa9\ub85d \ubc0f \ud398\uc774\uc9d5 \ucc98\ub9ac\n\n**\uc8fc\uc694 \uba54\uc18c\ub4dc**:\n- `setTable()`: \ud14c\uc774\ube14 \uc9c0\uc815\n- `setListNum()`: \ubaa9\ub85d \uac1c\uc218 \uc9c0\uc815\n- `addWhere()`: \uc870\uac74 \ucd94\uac00\n- `addSearch()`: \uac80\uc0c9 \uc870\uac74 \ucd94\uac00\n- `setOrderBy()`: \uc815\ub82c \uc9c0\uc815\n- `getDataSet()`: \ubaa9\ub85d \ub370\uc774\ud130 \uac00\uc838\uc624\uae30\n- `getTotalNum()`: \uc804\uccb4 \uac1c\uc218 \uac00\uc838\uc624\uae30\n- `getPaging()`: \ud398\uc774\uc9c0 \ub124\ube44\uac8c\uc774\uc158 \uc0dd\uc131\n\n### Auth\n\uc778\uc99d \ucc98\ub9ac\n\n**\uc8fc\uc694 \uba54\uc18c\ub4dc**:\n- `isValid()`: \uc778\uc99d \uc720\ud6a8\uc131 \uccb4\ud06c\n- `put()`: \uc778\uc99d \uc815\ubcf4 \uc124\uc815\n- `get()` / `getString()` / `getInt()`: \uc778\uc99d \uc815\ubcf4 \uac00\uc838\uc624\uae30\n- `save()`: \uc778\uc99d \uc815\ubcf4 \uc800\uc7a5\n- `delete()`: \uc778\uc99d \uc815\ubcf4 \uc0ad\uc81c\n\n### Config\n\ud658\uacbd\uc124\uc815 \uad00\ub9ac\n\n**\uc8fc\uc694 \uba54\uc18c\ub4dc**:\n- `get()`: \uc124\uc815\uac12 \uac00\uc838\uc624\uae30\n- `getInt()`: \uc815\uc218\ud615 \uc124\uc815\uac12 \uac00\uc838\uc624\uae30\n- `getDocRoot()`: \ubb38\uc11c \ub8e8\ud2b8 \uacbd\ub85c\n- `getDataDir()`: \ub370\uc774\ud130 \ub514\ub809\ud1a0\ub9ac \uacbd\ub85c\n- `getTplRoot()`: \ud15c\ud50c\ub9bf \ub8e8\ud2b8 \uacbd\ub85c\n- `reload()`: \uc124\uc815 \uc7ac\ub85c\ub4dc\n\n---\n\n## \uac1c\ubc1c \ud504\ub85c\uc138\uc2a4\n\n### 1. \ud658\uacbd \uad6c\ucd95\n1. WAS \uc124\uce58 (Resin, Tomcat \ub4f1)\n2. \ub9d1\uc740\ud504\ub808\uc784\uc6cc\ud06c \ub77c\uc774\ube0c\ub7ec\ub9ac \uc124\uce58\n3. \ud658\uacbd\uc124\uc815 \ud30c\uc77c \uc791\uc131\n\n### 2. \uae30\ubcf8 \uad6c\uc870 \uc0dd\uc131\n1. init.jsp \uc791\uc131\n2. \ud3f4\ub354 \uad6c\uc870 \uc0dd\uc131\n3. config.xml \uc124\uc815\n\n### 3. \uae30\ub2a5 \uac1c\ubc1c\n1. DAO \ud074\ub798\uc2a4 \uc791\uc131 (Model)\n2. JSP \ud30c\uc77c \uc791\uc131 (Controller)\n3. HTML \ud15c\ud50c\ub9bf \uc791\uc131 (View)\n\n### 4. \ud14c\uc2a4\ud2b8 \ubc0f \ubc30\ud3ec\n1. \uae30\ub2a5 \ud14c\uc2a4\ud2b8\n2. \ub514\ubc84\uae45\n3. \ubc30\ud3ec\n\n---\n\n## \ub2e4\uc74c \ub2e8\uacc4\n\n- [\uc124\uce58 \ubc0f \ud658\uacbd\uc124\uc815](installation.md)\uc73c\ub85c \uc774\ub3d9\ud558\uc5ec \ud504\ub808\uc784\uc6cc\ud06c\ub97c \uc124\uce58\ud558\uc138\uc694.\n\n---\n\n[\u2190 \ubaa9\ucc28\ub85c \ub3cc\uc544\uac00\uae30](README.md) | [\ub2e4\uc74c: \uc124\uce58 \ubc0f \ud658\uacbd\uc124\uc815 \u2192](installation.md)",
  "sections": [
    {
      "heading": "\uac1c\uc694",
      "content": "\ub9d1\uc740\ud504\ub808\uc784\uc6cc\ud06c\ub294 \uc790\ubc14 \uc6f9\uac1c\ubc1c \ud504\ub808\uc784\uc6cc\ud06c\uc785\ub2c8\ub2e4. WAS(Web Application Server) \uc548\uc5d0\uc11c \uad6c\ub3d9\ub418\ub294 \uc194\ub8e8\uc158\uc774\uba70, \uac04\uacb0\ud558\uace0 \ud6a8\uc728\uc801\uc778 \uc6f9 \uc560\ud50c\ub9ac\ucf00\uc774\uc158 \uac1c\ubc1c\uc744 \uc9c0\uc6d0\ud569\ub2c8\ub2e4."
    },
    {
      "heading": "\uc8fc\uc694 \ud2b9\uc9d5",
      "content": "\ud15c\ud50c\ub9bf \uc5d4\uc9c4, DataSet \uac1d\uccb4, \ub370\uc774\ud130\ubca0\uc774\uc2a4 \ucd94\uc0c1\ud654, \uc720\ud6a8\uc131 \uac80\uc99d, \uac04\ub2e8\ud55c \uc124\uc815 \ub4f1 5\uac00\uc9c0 \uc8fc\uc694 \ud2b9\uc9d5\uc744 \uc124\uba85\ud569\ub2c8\ub2e4."
    },
    {
      "heading": "\uc544\ud0a4\ud14d\ucc98",
      "content": "MVC \ud328\ud134 \uae30\ubc18\uc758 \uc544\ud0a4\ud14d\ucc98\ub85c Controller(JSP), Model(DAO/DataSet), View(HTML \ud15c\ud50c\ub9bf)\ub85c \uad6c\uc131\ub429\ub2c8\ub2e4."
    },
    {
      "heading": "\ud575\uc2ec \ud074\ub798\uc2a4",
      "content": "Malgn, Form, Page, DataObject, DataSet, ListManager, Auth, Config \ub4f1\uc758 \ud575\uc2ec \ud074\ub798\uc2a4\uc640 \uc8fc\uc694 \uba54\uc18c\ub4dc\ub97c \uc18c\uac1c\ud569\ub2c8\ub2e4."
    },
    {
      "heading": "\uac1c\ubc1c \ud504\ub85c\uc138\uc2a4",
      "content": "\ud658\uacbd \uad6c\ucd95, \uae30\ubcf8 \uad6c\uc870 \uc0dd\uc131, \uae30\ub2a5 \uac1c\ubc1c, \ud14c\uc2a4\ud2b8 \ubc0f \ubc30\ud3ec\uc758 4\ub2e8\uacc4 \uac1c\ubc1c \ud504\ub85c\uc138\uc2a4\ub97c \uc124\uba85\ud569\ub2c8\ub2e4."
    },
    {
      "heading": "\ub2e4\uc74c \ub2e8\uacc4",
      "content": "\uc124\uce58 \ubc0f \ud658\uacbd\uc124\uc815\uc73c\ub85c \uc774\ub3d9\ud558\uc5ec \ud504\ub808\uc784\uc6cc\ud06c\ub97c \uc124\uce58\ud558\uc138\uc694."
    }
  ],
  "related_docs": ["installation", "getting-started", "configuration", "template", "database", "dataobject", "dataset", "form-validation", "list-search"],
  "related_classes": ["Malgn", "Form", "Page", "DataObject", "DataSet", "ListManager", "Auth"]
}